LICENSE
README.md
setup.py
bf_scrapy_redis_sentinel.egg-info/PKG-INFO
bf_scrapy_redis_sentinel.egg-info/SOURCES.txt
bf_scrapy_redis_sentinel.egg-info/dependency_links.txt
bf_scrapy_redis_sentinel.egg-info/top_level.txt
bf_scrapy_redis_sentinel.egg-info/zip-safe
scrapy_redis_sentinel/__init__.py
scrapy_redis_sentinel/bloomfilter.py
scrapy_redis_sentinel/connection.py
scrapy_redis_sentinel/defaults.py
scrapy_redis_sentinel/dupefilter.py
scrapy_redis_sentinel/picklecompat.py
scrapy_redis_sentinel/pipelines.py
scrapy_redis_sentinel/queue.py
scrapy_redis_sentinel/scheduler.py
scrapy_redis_sentinel/spiders.py
scrapy_redis_sentinel/stats.py
scrapy_redis_sentinel/utils.py